Metadata-Version: 2.1
Name: animatebar
Version: 1.0
Summary: A Python package to generate animated bar plots with Plotly
Author: Ranjit Maity
Classifier: Programming Language :: Python :: 3
Classifier: License :: OSI Approved :: MIT License
Classifier: Operating System :: OS Independent
